{
  "client": [
    "/assets/vendors.e1c92e3d.js",
    "/assets/client.db5aafc2.js"
  ],
  "home": [
    "/assets/754.fe194c88.chunk.js",
    "/assets/259.9cab0362.chunk.js",
    "/assets/593.be845d70.chunk.js",
    "/assets/675.bf0b28c2.chunk.js",
    "/assets/home.31d39470.chunk.js"
  ],
  "write-editor": [
    "/assets/754.fe194c88.chunk.js",
    "/assets/675.bf0b28c2.chunk.js",
    "/assets/write-editor.a550ea21.chunk.js"
  ],
  "allofauthor": [
    "/assets/754.fe194c88.chunk.js",
    "/assets/259.9cab0362.chunk.js",
    "/assets/13.99be7865.chunk.js",
    "/assets/675.bf0b28c2.chunk.js",
    "/assets/allofauthor.85225724.chunk.js"
  ],
  "reset-password": [
    "/assets/754.fe194c88.chunk.js",
    "/assets/675.bf0b28c2.chunk.js",
    "/assets/reset-password.ff824109.chunk.js"
  ],
  "verify-email": [
    "/assets/754.fe194c88.chunk.js",
    "/assets/675.bf0b28c2.chunk.js",
    "/assets/verify-email.74b6eb89.chunk.js"
  ],
  "read-experience": [
    "/assets/754.fe194c88.chunk.js",
    "/assets/259.9cab0362.chunk.js",
    "/assets/593.be845d70.chunk.js",
    "/assets/122.b71063e4.chunk.js",
    "/assets/675.bf0b28c2.chunk.js",
    "/assets/read-experience.f5a8c421.chunk.js"
  ],
  "not-found": [
    "/assets/754.fe194c88.chunk.js",
    "/assets/675.bf0b28c2.chunk.js",
    "/assets/not-found.ac667f4f.chunk.js"
  ],
  "components-Link": [],
  "components-Inspire": [
    "/assets/components-Inspire.10f53ba0.chunk.js"
  ],
  "Authenticate": [
    "/assets/Authenticate.5d7c9526.chunk.js"
  ],
  "components-UIElements-MobileNotSupported": [
    "/assets/UIElements-MobileNotSupported.860e39b4.chunk.js"
  ],
  "Editor": [
    "/assets/259.9cab0362.chunk.js",
    "/assets/593.be845d70.chunk.js",
    "/assets/122.b71063e4.chunk.js",
    "/assets/292.ec43cf57.chunk.js",
    "/assets/296.eb179297.chunk.js",
    "/assets/Editor.c3bf873b.chunk.js"
  ],
  "Thoughts": [
    "/assets/Thoughts.e1dd1c4c.chunk.js"
  ],
  "GetStartedButton": [
    "/assets/GetStartedButton.65ed7c8d.chunk.js"
  ],
  "UIElements-InspireText": [
    "/assets/UIElements-InspireText.a7430793.chunk.js"
  ],
  "Login": [
    "/assets/702.c9d742f4.chunk.js",
    "/assets/Login.6adf5461.chunk.js"
  ],
  "Link": [],
  "Register": [
    "/assets/702.c9d742f4.chunk.js",
    "/assets/Register.d58111c2.chunk.js"
  ],
  "null": [
    "/assets/446.679f332d.chunk.js"
  ],
  "UIElements-MobileNotSupported": [
    "/assets/UIElements-MobileNotSupported.860e39b4.chunk.js"
  ],
  "UIElements-AuthFlow-ErrorMessage": [],
  "ReadThoughts": [
    "/assets/ReadThoughts.f6df4387.chunk.js"
  ],
  "ExpressThoughts": [
    "/assets/292.ec43cf57.chunk.js",
    "/assets/ExpressThoughts.cd56a83c.chunk.js"
  ]
}